{
  "schemaVersion": 1,
  "id": "bettersodiumvideosettingsbutton",
  "version": "1.0.2",
  "name": "Better Sodium Video Settings Button",
  "description": "Changes the Sodium Video settings back to the original, You can get to the Sodium Video Settings page via the Vanilla video settings page.",
  "authors": [
    "LimeShulkerBox"
  ],
  "contact": {
    "homepage": "https://www.curseforge.com/minecraft/mc-mods/better-sodium-button",
    "sources": "https://github.com/LimeShulkerBox/better-sodium-video-settings"
  },
  "license": "MIT",
  "icon": "assets/bettersodiumbutton/icon.png",
  "environment": "client",
  "entrypoints": {
    "client": [
      "com.limeshulkerbox.bettersodiumvideosettingsbutton.client.BetterSodiumVideoSettingsButtonClient"
    ]
  },
  "mixins": [
    "BetterSodiumVideoSettingsButton.mixins.json"
  ],
  "depends": {
    "sodium": "*",
    "fabricloader": ">=0.10.8",
    "minecraft": "1.16.x"
  },
  "custom": {
    "modmenu:clientsideOnly": true
  }
}